README.md
dnstwist.py
setup.py
dnstwist_mod.egg-info/PKG-INFO
dnstwist_mod.egg-info/SOURCES.txt
dnstwist_mod.egg-info/dependency_links.txt
dnstwist_mod.egg-info/entry_points.txt
dnstwist_mod.egg-info/requires.txt
dnstwist_mod.egg-info/top_level.txt